out/__init__.py
out/out.py
simple_out-0.3.1.dist-info/licenses/LICENSE
simple_out-0.3.1.dist-info/METADATA
simple_out-0.3.1.dist-info/WHEEL
simple_out-0.3.1.dist-info/top_level.txt
simple_out-0.3.1.dist-info/RECORD
