Metadata-Version: 2.4
Name: simple_out
Version: 0.3.1
Summary: A simple way to print colored text in the terminal.
Home-page: https://github.com/2Bor3d/out
Author: 2Bor3d
License: GPLv3
Keywords: print,output,input
Classifier: Programming Language :: Python :: 3
Classifier: License :: OSI Approved :: GNU General Public License v3 (GPLv3)
Classifier: Operating System :: OS Independent
License-File: LICENSE
Dynamic: author
Dynamic: classifier
Dynamic: description
Dynamic: description-content-type
Dynamic: home-page
Dynamic: keywords
Dynamic: license
Dynamic: license-file
Dynamic: summary
